frps_st/__init__.py
frps_st/frpc.exe
frps_st/main.py
frps_st/utils.py
frps_st-0.1.0.dist-info/METADATA
frps_st-0.1.0.dist-info/WHEEL
frps_st-0.1.0.dist-info/entry_points.txt
frps_st-0.1.0.dist-info/top_level.txt
frps_st-0.1.0.dist-info/RECORD
