Metadata-Version: 2.1
Name: frps-st
Version: 0.1.0
Summary: A library for testing download speed using frpc
Home-page: https://github.com/OnlineMo/Frps-ST
Author: Tac
Author-email: Tab@tac.us.kg
License: UNKNOWN
Platform: UNKNOWN
Classifier: Programming Language :: Python :: 3
Classifier: License :: OSI Approved :: MIT License
Classifier: Operating System :: OS Independent
Requires-Python: >=3.6
Requires-Dist: requests
